Metadata-Version: 2.1
Name: fuzz-dict
Version: 0.0.4
Author: Davide Di Grande
Author-email: davidedigrande.dev@gmail.com
Project-URL: Source, https://github.com/davidedigrande/fuzz-dict
License-File: LICENSE
